zx.py
zxpy-1.6.4.dist-info/LICENSE
zxpy-1.6.4.dist-info/METADATA
zxpy-1.6.4.dist-info/WHEEL
zxpy-1.6.4.dist-info/entry_points.txt
zxpy-1.6.4.dist-info/top_level.txt
zxpy-1.6.4.dist-info/RECORD
